graphqldomain.py
graphqldomain-1.0.0.dist-info/LICENSE.rst
graphqldomain-1.0.0.dist-info/WHEEL
graphqldomain-1.0.0.dist-info/METADATA
graphqldomain-1.0.0.dist-info/RECORD
