Metadata-Version: 2.3
Name: graphqldomain
Version: 1.0.0
Summary: A GraphQL domain for Sphinx.
Author-email: Ashley Whetter <ashley@awhetter.co.uk>
Requires-Python: >=3.9
Classifier: Development Status :: 5 - Production/Stable
Classifier: Environment :: Plugins
Classifier: Framework :: Sphinx :: Domain
Classifier: Framework :: Sphinx :: Extension
Classifier: Intended Audience :: Developers
Classifier: License :: OSI Approved :: MIT License
Classifier: Natural Language :: English
Classifier: Programming Language :: Python
Classifier: Programming Language :: Python :: 3
Classifier: Programming Language :: Python :: 3.9
Classifier: Programming Language :: Python :: 3.10
Classifier: Programming Language :: Python :: 3.11
Classifier: Programming Language :: Python :: 3.12
Classifier: Programming Language :: Python :: 3.13
Requires-Dist: graphql-core>=1.1
Requires-Dist: sphinx>=4.0
Project-URL: Documentation, https://graphqldomain.readthedocs.org
Project-URL: Source, https://github.com/AWhetter/graphqldomain
